qt_object_viewer
