Metadata-Version: 1.0
Name: qt-object-viewer
Version: 1.0.2
Summary: qt tree model + tree viewer for nested objects
Home-page: UNKNOWN
Author: Uwe Schmitt
Author-email: uwe.schmitt@id.ethz.ch
License: UNKNOWN
Platform: any
